pacotepypi/modulo.py
pacotes-0.0.1.dist-info/LICENSE
pacotes-0.0.1.dist-info/METADATA
pacotes-0.0.1.dist-info/WHEEL
pacotes-0.0.1.dist-info/top_level.txt
pacotes-0.0.1.dist-info/RECORD
