Metadata-Version: 2.1
Name: pacotes
Version: 0.0.1
Summary: Pacote python para exibir número de 1 a 9
Home-page: UNKNOWN
Author: Let lima
Author-email: lwtferr@gmail.com
License: MIT License
Keywords: Pacote
Platform: UNKNOWN
License-File: LICENSE
Requires-Dist: numpy
